pytorch_tools/__init__.py
pytorch_tools/detection_models/__init__.py
pytorch_tools/detection_models/efficientdet.py
pytorch_tools/detection_models/retinanet.py
pytorch_tools/fit_wrapper/README.md
pytorch_tools/fit_wrapper/__init__.py
pytorch_tools/fit_wrapper/callbacks.py
pytorch_tools/fit_wrapper/state.py
pytorch_tools/fit_wrapper/utils.py
pytorch_tools/fit_wrapper/wrapper.py
pytorch_tools/losses/README.md
pytorch_tools/losses/__init__.py
pytorch_tools/losses/angular.py
pytorch_tools/losses/base.py
pytorch_tools/losses/detection.py
pytorch_tools/losses/dice_jaccard.py
pytorch_tools/losses/focal.py
pytorch_tools/losses/functional.py
pytorch_tools/losses/hinge.py
pytorch_tools/losses/huber.py
pytorch_tools/losses/kld.py
pytorch_tools/losses/lovasz.py
pytorch_tools/losses/smooth.py
pytorch_tools/losses/vgg_loss.py
pytorch_tools/losses/wing_loss.py
pytorch_tools/metrics/README.md
pytorch_tools/metrics/__init__.py
pytorch_tools/metrics/accuracy.py
pytorch_tools/metrics/dice_jaccard.py
pytorch_tools/metrics/psnr.py
pytorch_tools/models/README.md
pytorch_tools/models/__init__.py
pytorch_tools/models/b_model.py
pytorch_tools/models/bit_resnet.py
pytorch_tools/models/cmodel.py
pytorch_tools/models/densenet.py
pytorch_tools/models/efficientnet.py
pytorch_tools/models/hrnet.py
pytorch_tools/models/preprocessing.py
pytorch_tools/models/resnet.py
pytorch_tools/models/tresnet.py
pytorch_tools/models/vgg.py
pytorch_tools/modules/__init__.py
pytorch_tools/modules/activated_batch_channel_norm.py
pytorch_tools/modules/activated_batch_norm.py
pytorch_tools/modules/activated_group_norm.py
pytorch_tools/modules/activated_no_norm.py
pytorch_tools/modules/activations.py
pytorch_tools/modules/bifpn.py
pytorch_tools/modules/conv.py
pytorch_tools/modules/decoder.py
pytorch_tools/modules/fpn.py
pytorch_tools/modules/mlp.py
pytorch_tools/modules/pooling.py
pytorch_tools/modules/residual.py
pytorch_tools/modules/spatial_ocr_block.py
pytorch_tools/modules/tf_same_ops.py
pytorch_tools-0.5.7.dist-info/LICENSE
pytorch_tools-0.5.7.dist-info/METADATA
pytorch_tools-0.5.7.dist-info/WHEEL
pytorch_tools-0.5.7.dist-info/top_level.txt
pytorch_tools-0.5.7.dist-info/RECORD
