Metadata-Version: 2.1
Name: pytorch_tools
Version: 0.5.7
Summary: Tool box for PyTorch
Author-email: Emil Zakirov <bonlimezak@gmail.com>
License: MIT License
Classifier: Programming Language :: Python :: 3
Classifier: Operating System :: OS Independent
Requires-Python: >=3.10
License-File: LICENSE
Requires-Dist: torch >=1.6
Requires-Dist: loguru >=0.4.1
Requires-Dist: tqdm >=4.49
Requires-Dist: matplotlib >=3.7.1
